CHANGES.txt
LICENSE.txt
MANIFEST.in
README.md
setup.cfg
setup.py
docs/index.md
sparklingpandas/__init__.py
sparklingpandas/dataframe.py
sparklingpandas/groupby.py
sparklingpandas/pcontext.py
sparklingpandas/prdd.py
sparklingpandas/pstatcounter.py
sparklingpandas/pstats.py
sparklingpandas/utils.py
sparklingpandas.egg-info/#SOURCES.txt#
sparklingpandas.egg-info/PKG-INFO
sparklingpandas.egg-info/SOURCES.txt
sparklingpandas.egg-info/dependency_links.txt
sparklingpandas.egg-info/requires.txt
sparklingpandas.egg-info/top_level.txt
sparklingpandas/jar/__init__.py
sparklingpandas/jar/sparklingpandas-assembly-0.0.4-SNAPSHOT.jar
sparklingpandas/shell/__init__.py
sparklingpandas/shell/shell.py
sparklingpandas/shell/sparklingpandasshell
sparklingpandas/test/__init__.py
sparklingpandas/test/dataframe_tests.py
sparklingpandas/test/dataload_tests.py
sparklingpandas/test/group_by_tests.py
sparklingpandas/test/pandas_groupby_tests.py
sparklingpandas/test/pcontext_tests.py
sparklingpandas/test/sp_test_case.py
sparklingpandas/test/utils.py
sparklingpandas/test/vectorized_op_timing.py