Metadata-Version: 1.0
Name: sparklingpandas
Version: 0.0.6
Summary: Enable a Pandas like API on PySpark
Home-page: https://github.com/sparklingpandas/sparklingpandas
Author: Holden Karau, Juliet Hougland
Author-email: holden@pigscanfly.ca, juliet@cloudera.com
License: LICENSE.txt
Platform: UNKNOWN
